README.md
setup.py
Plugwise_Smile/Smile.py
Plugwise_Smile/__init__.py
Plugwise_Smile.egg-info/PKG-INFO
Plugwise_Smile.egg-info/SOURCES.txt
Plugwise_Smile.egg-info/dependency_links.txt
Plugwise_Smile.egg-info/not-zip-safe
Plugwise_Smile.egg-info/requires.txt
Plugwise_Smile.egg-info/top_level.txt