Metadata-Version: 1.0
Name: Plugwise-Smile
Version: 1.0.0
Summary: Plugwise_Smile (Anna/Adam/P1) API to use in conjunction with Home Assistant.
Home-page: https://github.com/plugwise/Plugwise-Smile
Author: Plugwise
Author-email: info@compa.nl
License: MIT
Keywords: HomeAssistant HA Home Assistant Anna Adam P1 Smile Plugwise
Platform: UNKNOWN
